{
    "data": [
        {
            "school": "苗栗縣國立苑裡高中",
            "id": "01",
            "name": "鍾政岳"
        },
        {
            "school": "苗栗縣立興華高中",
            "id": "02",
            "name": "賴玉萍"
        },
        {
            "school": "苗栗縣國立竹南高中",
            "id": "03",
            "name": "林靜怡"
        },
        {
            "school": "台中市國立大甲高中",
            "id": "04",
            "name": "林秋萍"
        },
        {
            "school": "台中市國立臺中一中",
            "id": "05",
            "name": "蕭斐丹"
        },
        {
            "school": "台中市國立文華高中",
            "id": "06",
            "name": "高嘉宏"
        },
        {
            "school": "台中市私立大明高中",
            "id": "07",
            "name": "呂建孟"
        },
        {
            "school": "台中市私立青年高中",
            "id": "08",
            "name": "張伍庭"
        },
        {
            "school": "台中市國立東勢高工",
            "id": "09",
            "name": "梁書平"
        },
        {
            "school": "彰化縣立二林高中",
            "id": "10",
            "name": "施潤蒨"
        },
        {
            "school": "彰化縣立彰化藝術高中",
            "id": "11",
            "name": "柳皓中"
        },
        {
            "school": "南投縣國立南投高中",
            "id": "12",
            "name": "高嘉君"
        },
        {
            "school": "南投縣國立暨大學附中",
            "id": "13",
            "name": "蕭又嘉"
        },
        {
            "school": "南投縣國立竹山高中",
            "id": "14",
            "name": "張仕清"
        },
        {
            "school": "南投縣立旭光高中",
            "id": "15",
            "name": "謝欣茹"
        },
        {
            "school": "雲林縣國立土庫商工",
            "id": "16",
            "name": "蔡璽琳"
        },
        {
            "school": "苗栗縣國立卓蘭實中國中部",
            "id": "17",
            "name": "羅郁惠"
        },
        {
            "school": "苗栗縣立大湖國中",
            "id": "18",
            "name": "呂佩芬"
        },
        {
            "school": "苗栗私立君毅高中國中部",
            "id": "19",
            "name": "黃文如"
        },
        {
            "school": "苗栗縣立通霄國中",
            "id": "20",
            "name": "鄭生祥"
        },
        {
            "school": "苗栗縣立明仁國中",
            "id": "21",
            "name": "邱永裕"
        },
        {
            "school": "台中市立大甲國中",
            "id": "22",
            "name": "陳??"
        },
        {
            "school": "台中市立居仁國中",
            "id": "23",
            "name": "徐韻琴"
        },
        {
            "school": "台中市立成功國中",
            "id": "24",
            "name": "洪良"
        },
        {
            "school": "台中市立中港高中國中部",
            "id": "25",
            "name": "王秋燕"
        },
        {
            "school": "台中市立四箴國中",
            "id": "26",
            "name": "呂昀潔"
        },
        {
            "school": "台中市立豐原國中",
            "id": "27",
            "name": "王建浩"
        },
        {
            "school": "彰化縣立和群國中",
            "id": "28",
            "name": "傅雅蘭"
        },
        {
            "school": "彰化縣立秀水國中",
            "id": "29",
            "name": "游淑凰"
        },
        {
            "school": "彰化縣立彰安國中",
            "id": "30",
            "name": "林秀珊"
        },
        {
            "school": "彰化縣立彰安國中",
            "id": "31",
            "name": "陳怡儒"
        },
        {
            "school": "南投縣立水里國中",
            "id": "32",
            "name": "鐘世閔"
        },
        {
            "school": "南投縣立草屯國中",
            "id": "33",
            "name": "黃建樹"
        },
        {
            "school": "南投縣立南投國中",
            "id": "34",
            "name": "林宜玟"
        },
        {
            "school": "南投縣立中興國中",
            "id": "35",
            "name": "蔡惠任"
        },
        {
            "school": "雲林縣私立正心高中國中部",
            "id": "36",
            "name": "廖定詳"
        },
        {
            "school": "雲林縣立斗六國中",
            "id": "37",
            "name": "張晏慈"
        },
        {
            "school": "雲林縣立東仁國中",
            "id": "38",
            "name": "陳盈帆"
        },
        {
            "school": "雲林縣立北港國中",
            "id": "39",
            "name": "鄭詠仁"
        },
        {
            "school": "雲林縣立斗南高中國中部",
            "id": "40",
            "name": "陳榮暐"
        },
        {
            "school": "苗栗縣立頭屋國中",
            "id": "41",
            "name": "陳至翔"
        }
    ],
    "area": "central"
}